Metadata-Version: 2.1
Name: xo-gd
Version: 3.2.6
Summary: Use Python Like You Never Have Before, Easy Acces To: Events and Triggers, Realtime MultiProcessing, Instant Dynamic DB, Filesytem & Web Watchdog, Sockets, MQTT, P2P, API Server, Supports Fast Prototyping To Large Scale Systems
Home-page: https://github.com/fire17/xo-gd
Author: Tami Bar
Author-email: fire17@gmail.com
License: BSD
Download-URL: https://github.com/fire17/xo-gd/tarball/3.2.6
Platform: UNKNOWN
Classifier: Development Status :: 3 - Alpha
Classifier: Intended Audience :: Developers
Classifier: Programming Language :: Python :: 3
